probflow/__init__.py
probflow/applications/__init__.py
probflow/applications/dense_classifier.py
probflow/applications/dense_regression.py
probflow/applications/linear_regression.py
probflow/applications/logistic_regression.py
probflow/applications/poisson_regression.py
probflow/callbacks/__init__.py
probflow/callbacks/callback.py
probflow/callbacks/early_stopping.py
probflow/callbacks/kl_weight_scheduler.py
probflow/callbacks/learning_rate_scheduler.py
probflow/callbacks/monitor_elbo.py
probflow/callbacks/monitor_metric.py
probflow/callbacks/monitor_parameter.py
probflow/callbacks/time_out.py
probflow/data/__init__.py
probflow/data/array_data_generator.py
probflow/data/data_generator.py
probflow/data/make_generator.py
probflow/distributions/__init__.py
probflow/distributions/bernoulli.py
probflow/distributions/categorical.py
probflow/distributions/cauchy.py
probflow/distributions/deterministic.py
probflow/distributions/dirichlet.py
probflow/distributions/gamma.py
probflow/distributions/hidden_markov_model.py
probflow/distributions/inverse_gamma.py
probflow/distributions/mixture.py
probflow/distributions/multivariate_normal.py
probflow/distributions/normal.py
probflow/distributions/one_hot_categorical.py
probflow/distributions/poisson.py
probflow/distributions/student_t.py
probflow/models/__init__.py
probflow/models/categorical_model.py
probflow/models/continuous_model.py
probflow/models/discrete_model.py
probflow/models/model.py
probflow/modules/__init__.py
probflow/modules/batch_normalization.py
probflow/modules/dense.py
probflow/modules/dense_network.py
probflow/modules/embedding.py
probflow/modules/module.py
probflow/modules/sequential.py
probflow/parameters/__init__.py
probflow/parameters/bounded_parameter.py
probflow/parameters/categorical_parameter.py
probflow/parameters/centered_parameter.py
probflow/parameters/deterministic_parameter.py
probflow/parameters/dirichlet_parameter.py
probflow/parameters/multivariate_normal_parameter.py
probflow-2.4.1.dist-info/LICENSE
probflow-2.4.1.dist-info/METADATA
probflow-2.4.1.dist-info/WHEEL
probflow-2.4.1.dist-info/top_level.txt
probflow-2.4.1.dist-info/RECORD
