Metadata-Version: 2.1
Name: probflow
Version: 2.4.1
Summary: A Python package for building Bayesian models with TensorFlow or PyTorch
Home-page: https://github.com/brendanhasz/probflow
Author: Brendan Hasz
Author-email: winsto99@gmail.com
License: MIT
Platform: UNKNOWN
Classifier: Programming Language :: Python :: 3
Classifier: License :: OSI Approved :: MIT License
Classifier: Operating System :: OS Independent
Classifier: Development Status :: 3 - Alpha
Requires-Dist: matplotlib (>=3.1.0)
Requires-Dist: numpy (>=1.17.0)
Requires-Dist: pandas (>=0.25.0)
Requires-Dist: cloudpickle (>=1.3)
Provides-Extra: dev
Requires-Dist: autoflake (>=1.4) ; extra == 'dev'
Requires-Dist: black (>=19.10b0) ; extra == 'dev'
Requires-Dist: bumpversion ; extra == 'dev'
Requires-Dist: flake8 (>=3.8.3) ; extra == 'dev'
Requires-Dist: isort (>=5.1.2) ; extra == 'dev'
Requires-Dist: pytest (>=6.0.0rc1) ; extra == 'dev'
Requires-Dist: pytest-cov (>=2.7.1) ; extra == 'dev'
Requires-Dist: sphinx (>=3.1.2) ; extra == 'dev'
Requires-Dist: sphinx-tabs (>=1.1.13) ; extra == 'dev'
Requires-Dist: sphinx-rtd-theme (>=0.5.0) ; extra == 'dev'
Requires-Dist: setuptools (>=49.1.0) ; extra == 'dev'
Requires-Dist: twine (>=3.2.0) ; extra == 'dev'
Requires-Dist: wheel (>=0.34.2) ; extra == 'dev'
Provides-Extra: docs
Requires-Dist: tensorflow (>=2.2.0) ; extra == 'docs'
Requires-Dist: tensorflow-probability (>=0.10.0) ; extra == 'docs'
Requires-Dist: sphinx-tabs (>=1.1.13) ; extra == 'docs'
Provides-Extra: pytorch
Requires-Dist: torch (>=1.5.0) ; extra == 'pytorch'
Provides-Extra: tensorflow
Requires-Dist: tensorflow (>=2.2.0) ; extra == 'tensorflow'
Requires-Dist: tensorflow-probability (>=0.10.0) ; extra == 'tensorflow'
Provides-Extra: tensorflow_gpu
Requires-Dist: tensorflow-gpu (>=2.2.0) ; extra == 'tensorflow_gpu'
Requires-Dist: tensorflow-probability (>=0.10.0) ; extra == 'tensorflow_gpu'
